MANIFEST.in
README.md
setup.py
python_linkedin_client/__init__.py
python_linkedin_client/linkedinclient.py
python_linkedin_client.egg-info/PKG-INFO
python_linkedin_client.egg-info/SOURCES.txt
python_linkedin_client.egg-info/dependency_links.txt
python_linkedin_client.egg-info/requires.txt
python_linkedin_client.egg-info/top_level.txt