Metadata-Version: 1.1
Name: python-linkedin-client
Version: 1.0.1
Summary: LinkedIn API in python
Home-page: https://github.com/mingchen/python-linkedin-client
Author: Ming Chen
Author-email: mockey.chen@gmail.com
License: MIT
Download-URL: https://github.com/mingchen/python-linkedin-client/releases
Keywords: linkedin,rest api,oauth2,linkedin profile
Platform: UNKNOWN
Classifier: Development Status :: 5 - Production/Stable
Classifier: Environment :: Web Environment
Classifier: Intended Audience :: Developers
Classifier: License :: OSI Approved :: MIT License
Classifier: Natural Language :: English
Classifier: Operating System :: OS Independent
Classifier: Topic :: Internet :: WWW/HTTP
